README.md
setup.py
aruudy/__init__.py
aruudy.egg-info/PKG-INFO
aruudy.egg-info/SOURCES.txt
aruudy.egg-info/dependency_links.txt
aruudy.egg-info/top_level.txt
aruudy/lists/__init__.py
aruudy/lists/change.py
aruudy/lists/const.py
aruudy/poetry/__init__.py
aruudy/poetry/foot.py
aruudy/poetry/meter.py
aruudy/poetry/prosody.py
aruudy/web/__init__.py
aruudy/web/api.py
aruudy/web/cgi.py
exec/aruudy
exec/aruudy_flask