Metadata-Version: 2.1
Name: aruudy
Version: 0.5.1
Summary: Arabic poetry package
Home-page: https://github.com/kariminf/aruudy
Author: Abdelkrime Aries
Author-email: kariminfo0@gmail.com
License: Apache-2.0
Keywords: arabic nlp languages poetry prosody
Platform: UNKNOWN
Classifier: Development Status :: 3 - Alpha
Classifier: Environment :: Console
Classifier: Intended Audience :: Developers
Classifier: Intended Audience :: Education
Classifier: Intended Audience :: Science/Research
Classifier: License :: OSI Approved :: Apache Software License
Classifier: Natural Language :: Arabic
Classifier: Operating System :: OS Independent
Classifier: Programming Language :: Python :: 2.7
Classifier: Programming Language :: Python :: 3.6
Classifier: Topic :: Software Development :: Build Tools
Classifier: Topic :: Education
Classifier: Topic :: Text Processing :: Linguistic
